tlacacoca/__init__.py
tlacacoca/logging/__init__.py
tlacacoca/logging/structured.py
tlacacoca/middleware/__init__.py
tlacacoca/middleware/access_control.py
tlacacoca/middleware/base.py
tlacacoca/middleware/certificate_auth.py
tlacacoca/middleware/rate_limit.py
tlacacoca/py.typed
tlacacoca/security/__init__.py
tlacacoca/security/certificates.py
tlacacoca/security/tls.py
tlacacoca/security/tofu.py
tlacacoca-0.1.4.dist-info/WHEEL
tlacacoca-0.1.4.dist-info/METADATA
tlacacoca-0.1.4.dist-info/RECORD
