Metadata-Version: 2.3
Name: tlacacoca
Version: 0.1.4
Summary: Shared foundation library for TLS-based protocol implementations
Author: Alan Velasco
Author-email: Alan Velasco <alanvelasco.a@gmail.com>
Requires-Dist: cryptography>=46.0.3
Requires-Dist: structlog>=25.5.0
Requires-Dist: tomli>=2.0.0 ; python_full_version < '3.11'
Requires-Dist: tomli-w>=1.2.0
Requires-Python: >=3.10
